pygrin/__init__.py
pygrin/pygrin.py
pygrin-0.6.1.dist-info/licenses/LICENSE.txt
pygrin-0.6.1.dist-info/METADATA
pygrin-0.6.1.dist-info/WHEEL
pygrin-0.6.1.dist-info/top_level.txt
pygrin-0.6.1.dist-info/RECORD
